wax.py
wacks-0.1.0b2.dist-info/METADATA
wacks-0.1.0b2.dist-info/WHEEL
wacks-0.1.0b2.dist-info/entry_points.txt
wacks-0.1.0b2.dist-info/top_level.txt
wacks-0.1.0b2.dist-info/RECORD
